pydarknetserver/__init__.py
pydarknetserver/pydarknetserver.py
pydarknetserver-0.2.0.dist-info/AUTHORS.rst
pydarknetserver-0.2.0.dist-info/LICENSE
pydarknetserver-0.2.0.dist-info/METADATA
pydarknetserver-0.2.0.dist-info/WHEEL
pydarknetserver-0.2.0.dist-info/top_level.txt
pydarknetserver-0.2.0.dist-info/RECORD
