Metadata-Version: 2.1
Name: pydarknetserver
Version: 0.2.0
Summary: Python Darknet Server
Home-page: https://github.com/yoyonel/pydarknetserver
Author: Lionel Atty
Author-email: yoyonel@hotmail.com
License: MIT license
Keywords: pydarknetserver
Platform: UNKNOWN
Classifier: Development Status :: 2 - Pre-Alpha
Classifier: Intended Audience :: Developers
Classifier: License :: OSI Approved :: MIT License
Classifier: Natural Language :: English
Classifier: Programming Language :: Python :: 3.6
Classifier: Programming Language :: Python :: 3.7
Classifier: Programming Language :: Python :: 3.8
Requires-Python: >=3.6
